esycord/__init__.py
esycord/__internals.py
esycord/__main__.py
esycord/data.py
esycord/esycord.py
esycord-1.6.6.dist-info/METADATA
esycord-1.6.6.dist-info/WHEEL
esycord-1.6.6.dist-info/RECORD
