Metadata-Version: 2.4
Name: esycord
Version: 1.6.6
Summary: The most beginner friendly discord package
Project-URL: Repository, https://github.com/Aayush-Srivastava2410/esycord
Project-URL: Issues, https://github.com/Aayush-Srivastava2410/esycord/issues
Project-URL: Documentation, https://github.com/Aayush-Srivastava2410/esycord/wiki
Project-URL: Discord, https://discord.com/users/795873954668871731
Author: Aayush Srivastava
License-Expression: MIT
Keywords: Discord bot maker,beginner discord,discord,discord simple,easycord,esycord,ezycord
Classifier: Development Status :: 5 - Production/Stable
Classifier: Intended Audience :: Developers
Classifier: License :: OSI Approved :: MIT License
Classifier: Programming Language :: Python :: 3.5
Classifier: Programming Language :: Python :: 3.6
Classifier: Programming Language :: Python :: 3.7
Classifier: Programming Language :: Python :: 3.8
Classifier: Programming Language :: Python :: 3.9
Classifier: Programming Language :: Python :: 3.10
Classifier: Programming Language :: Python :: 3.11
Classifier: Programming Language :: Python :: 3.12
Classifier: Topic :: Software Development :: Build Tools
Requires-Python: >=3.5
Requires-Dist: aiohttp>=3.9.5
Requires-Dist: colorama
Requires-Dist: discord
Requires-Dist: pynacl>=1.5.0
Requires-Dist: requests
